wonplat/ModuleA.py
wonplat/__init__.py
wonplat-0.0.1.dist-info/LICENSE.txt
wonplat-0.0.1.dist-info/METADATA
wonplat-0.0.1.dist-info/WHEEL
wonplat-0.0.1.dist-info/top_level.txt
wonplat-0.0.1.dist-info/RECORD
