Metadata-Version: 2.1
Name: wonplat
Version: 0.0.1
Summary: A short description of your package
Home-page: https://github.com/WonderLari/Clifford-Sampling
Author: Xianghe Wang
Author-email: 3200104190@zju.edu.cn
Classifier: Programming Language :: Python :: 3
Classifier: License :: OSI Approved :: MIT License
Classifier: Operating System :: OS Independent
Requires-Python: >=3.6
License-File: LICENSE.txt
Requires-Dist: numpy (>=1.15.0)
Requires-Dist: scipy (>=1.3.0)
Requires-Dist: matplotlib (>=3.0.0)
Requires-Dist: stim (>=1.9.0)
Requires-Dist: qiskit (>=0.39.0)
